demographic_data_analytic/__init__.py
demographic_data_analytic/analytic.py
demographic_data_analytic/models.py
demographic_data_analytic/py.typed
demographic_data_analytic-0.1.0.dist-info/METADATA
demographic_data_analytic-0.1.0.dist-info/WHEEL
demographic_data_analytic-0.1.0.dist-info/RECORD
