Metadata-Version: 2.3
Name: demographic-data-analytic
Version: 0.1.0
Summary: Add your description here
Author-email: lunelson-deloitte <lunelson@deloitte.com>
Requires-Python: >=3.10
Requires-Dist: attrs>=24.2.0
Requires-Dist: loguru>=0.7.2
Requires-Dist: pyspark==3.5.2
